codepilot/__init__.py
codepilot/__main__.py
codepilot/app.py
codepilot/server.py
codepilot-0.1.0.dist-info/entry_points.txt
codepilot-0.1.0.dist-info/LICENSE
codepilot-0.1.0.dist-info/METADATA
codepilot-0.1.0.dist-info/WHEEL
codepilot-0.1.0.dist-info/RECORD
