Metadata-Version: 2.1
Name: codepilot
Version: 0.1.0
Summary: 
License: MIT
Author: vs4vijay
Author-email: vs4vijay@gmail.com
Requires-Python: >=3.10,<4.0
Classifier: License :: OSI Approved :: MIT License
Classifier: Programming Language :: Python :: 3
Classifier: Programming Language :: Python :: 3.10
Classifier: Programming Language :: Python :: 3.11
Requires-Dist: fastapi (>=0.103.2,<0.104.0)
Requires-Dist: pydantic (>=2.4.2,<3.0.0)
Requires-Dist: python-dotenv (>=1.0.0,<2.0.0)
